{
    "uuid": "bc453db1-baef-4971-bd1f-6df1350b5938",
    "type": "STANDARD",
    "sender": {
        "uuid": "f3a84fc8-33a8-4c70-a7c2-0b92b0da48e9",
        "name": "ФОП Кельнер Олег Володимирович",
        "firstName": null,
        "middleName": null,
        "lastName": null,
        "latinName": null,
        "contactPersonName": "Кельнер Олег Володимирович",
        "type": "PRIVATE_ENTREPRENEUR",
        "postId": null,
        "externalId": null,
        "uniqueRegistrationNumber": null,
        "counterpartyUuid": "ddd2d84f-db7b-460c-b68e-1c6df1917959",
        "addressId": 193185048,
        "addresses": [
            {
                "uuid": "98662ac3-9445-4725-b34f-0f55184feead",
                "addressId": 193185048,
                "address": {
                    "id": 193185048,
                    "postcode": "47707",
                    "region": "Тернопільська",
                    "district": "Тернопільський",
                    "city": "Біла",
                    "street": "Мазепи",
                    "houseNumber": "31",
                    "apartmentNumber": null,
                    "description": null,
                    "countryside": true,
                    "posteRestante": false,
                    "foreignStreetHouseApartment": null,
                    "detailedInfo": "Україна, 47707, Тернопільська, Тернопільський, Біла, Мазепи 31",
                    "created": "2021-08-05T16:19:31",
                    "lastModified": "2021-08-05T16:19:31",
                    "country": "UA"
                },
                "type": "PHYSICAL",
                "main": true
            }
        ],
        "phoneNumber": "+380675736709",
        "phones": [
            {
                "uuid": "87cc3b57-6686-4a12-9456-e60a7138b803",
                "phoneId": 171741581,
                "phoneNumber": "+380675736709",
                "type": "PERSONAL",
                "main": true
            }
        ],
        "email": "",
        "emails": [],
        "bankAccount": null,
        "tin": "3413904819",
        "postPayPaymentType": "POSTPAY_PAYMENT_CASH_ONLY",
        "accountType": {
            "type": "CORPORATE",
            "assignmentDate": "2021-03-01"
        },
        "resident": true,
        "GDPRRead": false,
        "GDPRAccept": false,
        "personalDataApproved": false,
        "checkOnDeliveryAllowed": true
    },
    "dropOffPostcode": "47707",
    "recipient": {
        "uuid": "4938e957-f2e8-4bfc-ba9b-665858c1509d",
        "name": "Прюшко Генадій",
        "firstName": "Генадій",
        "middleName": null,
        "lastName": "Прюшко",
        "latinName": null,
        "contactPersonName": null,
        "type": "INDIVIDUAL",
        "postId": null,
        "externalId": null,
        "uniqueRegistrationNumber": null,
        "counterpartyUuid": "ddd2d84f-db7b-460c-b68e-1c6df1917959",
        "addressId": 193186783,
        "addresses": [
            {
                "uuid": "3ac0a677-d1ba-40be-ba55-41831bfcb4a0",
                "addressId": 193186783,
                "address": {
                    "id": 193186783,
                    "postcode": "17461",
                    "region": "Чернігівська",
                    "district": "Ніжинський",
                    "city": "Нова Басань",
                    "street": "Шевченка",
                    "houseNumber": "43",
                    "apartmentNumber": null,
                    "description": null,
                    "countryside": true,
                    "posteRestante": false,
                    "foreignStreetHouseApartment": null,
                    "detailedInfo": "Україна, 17461, Чернігівська, Ніжинський, Нова Басань, Шевченка 43",
                    "created": "2021-08-05T16:24:20",
                    "lastModified": "2021-08-05T16:24:20",
                    "country": "UA"
                },
                "type": "PHYSICAL",
                "main": true
            }
        ],
        "phoneNumber": "+380633455399",
        "phones": [
            {
                "uuid": "b361b810-d0ba-4a4b-8334-ec0f1965bcb9",
                "phoneId": 157986102,
                "phoneNumber": "+380633455399",
                "type": "PERSONAL",
                "main": true
            }
        ],
        "email": "",
        "emails": [],
        "bankAccount": null,
        "postPayPaymentType": "POSTPAY_PAYMENT_CASH_ONLY",
        "accountType": {
            "type": "CORPORATE",
            "assignmentDate": "2021-03-01"
        },
        "resident": true,
        "GDPRRead": false,
        "GDPRAccept": false,
        "personalDataApproved": false,
        "checkOnDeliveryAllowed": true
    },
    "recipientPhone": "+380633455399",
    "recipientEmail": null,
    "recipientAddressId": 193186783,
    "senderAddressId": 193185048,
    "returnAddressId": 193185048,
    "shipmentGroupUuid": null,
    "externalId": null,
    "deliveryType": "W2W",
    "packageType": null,
    "onFailReceiveType": "RETURN",
    "barcode": "0503088679620",
    "weight": 2000,
    "length": 15,
    "width": 0,
    "height": 0,
    "declaredPrice": 233,
    "deliveryPrice": 31.66,
    "rawDeliveryPrice": 33.33,
    "returnDeliveryPrice": 15.83,
    "postPay": 233,
    "postPayUah": 233,
    "postPayDeliveryPrice": 10,
    "postPayRecipient": {
        "uuid": "f3a84fc8-33a8-4c70-a7c2-0b92b0da48e9",
        "name": "ФОП Кельнер Олег Володимирович",
        "type": "PRIVATE_ENTREPRENEUR",
        "counterpartyUuid": "ddd2d84f-db7b-460c-b68e-1c6df1917959",
        "postPayPaymentType": "POSTPAY_PAYMENT_CASH_ONLY",
        "bankAccount": null,
        "tin": "3413904819",
        "personalDataApproved": false
    },
    "currencyCode": null,
    "postPayCurrencyCode": null,
    "currencyExchangeRate": null,
    "discounts": [
        {
            "uuid": "133aaed9-47da-4574-b9a7-b785c83e003f",
            "name": "Он-лайн оформлення 5% Стандарт",
            "fromDate": "2018-01-01",
            "toDate": "2099-01-01",
            "value": 5.0,
            "category": "CONTRACT_DISCOUNT",
            "type": "BASE"
        }
    ],
    "lastModified": "2021-08-06T11:30:13",
    "description": null,
    "parcels": [
        {
            "uuid": "8d556237-5d5f-4942-b2a9-a67daaad6038",
            "name": null,
            "parcelNumber": 1,
            "barcode": "0503088679620",
            "contentsType": null,
            "weight": 2000,
            "length": 15,
            "width": null,
            "height": null,
            "declaredPrice": 233,
            "parcelItems": [],
            "description": null
        }
    ],
    "direction": {
        "regionSortingCenter": "Чернігів",
        "districtSortingCenter": null,
        "postOfficeNumber": "17461",
        "postOfficeName": "Ніжинський (Бобровицький)"
    },
    "lifecycle": {
        "status": "CREATED",
        "statusDate": "2021-08-06T11:30:13"
    },
    "deliveryDate": "2021-08-08T00:00:00",
    "calculationDescription": "Price=31.66: Calculation contains 1 parcels, new measures are weight:2000, length:15, height:0, width:0; price for the weight=0.00; tariff (STANDARD, COUNTRY, 2000 g, 15 cm)=31.00; countryside=0.00; declared price surcharge=2.33; Он-лайн оформлення 5% Стандарт=1.66; return delivery price=15.83",
    "availablePaymentTypes": [ "CARD_ON_SITE", "CARD", "CASH", "CASHLESS" ],
    "paidByRecipient": false,
    "postPayPaidByRecipient": true,
    "bulky": false,
    "fragile": false,
    "bees": false,
    "sms": false,
    "toReturnToSender": null,
    "documentBack": false,
    "checkOnDelivery": true,
    "transferPostPayToBankAccount": false,
    "deliveryPricePaid": false,
    "postPayPaid": false,
    "postPayDeliveryPricePaid": false,
    "packedBySender": false,
    "free": false,
    "withDeliveryNotification": false,
    "fittingAllowed": false
}